rulevis.py
internal/analyzer.py
internal/generator.py
internal/visualizer.py
internal/static/graph.js
internal/static/styles.css
internal/static/tutorial.js
rulevis-1.0.4.dist-info/licenses/LICENSE
rulevis-1.0.4.dist-info/METADATA
rulevis-1.0.4.dist-info/WHEEL
rulevis-1.0.4.dist-info/entry_points.txt
rulevis-1.0.4.dist-info/top_level.txt
rulevis-1.0.4.dist-info/RECORD
