Metadata-Version: 2.4
Name: rulevis
Version: 1.0.4
Summary: Interactive Wazuh Rule Graph Explorer
Author-email: Zafer Balkan <zafer@zaferbalkan.com>
License-Expression: MIT
Project-URL: Homepage, https://github.com/zbalkan/rulevis
Project-URL: Repository, https://github.com/zbalkan/rulevis
Project-URL: Issues, https://github.com/zbalkan/rulevis/issues
Keywords: wazuh,detection,security,monitoring,logging,siem
Classifier: Topic :: Security
Classifier: Topic :: System :: Logging
Classifier: Development Status :: 5 - Production/Stable
Classifier: Intended Audience :: Information Technology
Classifier: Programming Language :: Python :: 3
Classifier: Programming Language :: Python :: 3.9
Classifier: Programming Language :: Python :: 3.10
Classifier: Programming Language :: Python :: 3.11
Classifier: Programming Language :: Python :: 3.12
Classifier: Programming Language :: Python :: 3.13
Classifier: Programming Language :: Python :: 3.14
Requires-Python: >=3.9
License-File: LICENSE
Requires-Dist: Flask>=3.0.0
Requires-Dist: networkx
Dynamic: license-file
